[
  {
    "_key": "46842f93171d_hasLocation1",
    "_from": "DeviceProxyOut/46842f93171d_device1",
    "_to": "Location/46842f93171d_location5",
    "created": 1757725696.949166,
    "expired": 9223372036854775807,
    "tenant_46842f93171d_attr": "46842f93171d",
    "_fromType": "DeviceProxyOut",
    "_toType": "Location"
  },
  {
    "_key": "46842f93171d_hasLocation2",
    "_from": "DeviceProxyOut/46842f93171d_device2",
    "_to": "Location/46842f93171d_location9",
    "created": 1757725696.949169,
    "expired": 9223372036854775807,
    "tenant_46842f93171d_attr": "46842f93171d",
    "_fromType": "DeviceProxyOut",
    "_toType": "Location"
  },
  {
    "_key": "46842f93171d_hasLocation3",
    "_from": "DeviceProxyOut/46842f93171d_device3",
    "_to": "Location/46842f93171d_location2",
    "created": 1757725696.949172,
    "expired": 9223372036854775807,
    "tenant_46842f93171d_attr": "46842f93171d",
    "_fromType": "DeviceProxyOut",
    "_toType": "Location"
  },
  {
    "_key": "46842f93171d_hasLocation4",
    "_from": "DeviceProxyOut/46842f93171d_device4",
    "_to": "Location/46842f93171d_location5",
    "created": 1757725696.949174,
    "expired": 9223372036854775807,
    "tenant_46842f93171d_attr": "46842f93171d",
    "_fromType": "DeviceProxyOut",
    "_toType": "Location"
  },
  {
    "_key": "46842f93171d_hasLocation5",
    "_from": "DeviceProxyOut/46842f93171d_device5",
    "_to": "Location/46842f93171d_location8",
    "created": 1757725696.949176,
    "expired": 9223372036854775807,
    "tenant_46842f93171d_attr": "46842f93171d",
    "_fromType": "DeviceProxyOut",
    "_toType": "Location"
  },
  {
    "_key": "46842f93171d_hasLocation6",
    "_from": "DeviceProxyOut/46842f93171d_device6",
    "_to": "Location/46842f93171d_location5",
    "created": 1757725696.949178,
    "expired": 9223372036854775807,
    "tenant_46842f93171d_attr": "46842f93171d",
    "_fromType": "DeviceProxyOut",
    "_toType": "Location"
  },
  {
    "_key": "46842f93171d_hasLocation7",
    "_from": "DeviceProxyOut/46842f93171d_device7",
    "_to": "Location/46842f93171d_location3",
    "created": 1757725696.949181,
    "expired": 9223372036854775807,
    "tenant_46842f93171d_attr": "46842f93171d",
    "_fromType": "DeviceProxyOut",
    "_toType": "Location"
  },
  {
    "_key": "46842f93171d_hasLocation8",
    "_from": "DeviceProxyOut/46842f93171d_device8",
    "_to": "Location/46842f93171d_location7",
    "created": 1757725696.949183,
    "expired": 9223372036854775807,
    "tenant_46842f93171d_attr": "46842f93171d",
    "_fromType": "DeviceProxyOut",
    "_toType": "Location"
  },
  {
    "_key": "46842f93171d_hasLocation9",
    "_from": "DeviceProxyOut/46842f93171d_device9",
    "_to": "Location/46842f93171d_location1",
    "created": 1757725696.949185,
    "expired": 9223372036854775807,
    "tenant_46842f93171d_attr": "46842f93171d",
    "_fromType": "DeviceProxyOut",
    "_toType": "Location"
  },
  {
    "_key": "46842f93171d_hasLocation10",
    "_from": "DeviceProxyOut/46842f93171d_device10",
    "_to": "Location/46842f93171d_location1",
    "created": 1757725696.949187,
    "expired": 9223372036854775807,
    "tenant_46842f93171d_attr": "46842f93171d",
    "_fromType": "DeviceProxyOut",
    "_toType": "Location"
  },
  {
    "_key": "46842f93171d_hasLocation11",
    "_from": "DeviceProxyOut/46842f93171d_device11",
    "_to": "Location/46842f93171d_location8",
    "created": 1757725696.94919,
    "expired": 9223372036854775807,
    "tenant_46842f93171d_attr": "46842f93171d",
    "_fromType": "DeviceProxyOut",
    "_toType": "Location"
  },
  {
    "_key": "46842f93171d_hasLocation12",
    "_from": "DeviceProxyOut/46842f93171d_device12",
    "_to": "Location/46842f93171d_location2",
    "created": 1757725696.949192,
    "expired": 9223372036854775807,
    "tenant_46842f93171d_attr": "46842f93171d",
    "_fromType": "DeviceProxyOut",
    "_toType": "Location"
  },
  {
    "_key": "46842f93171d_hasLocation13",
    "_from": "DeviceProxyOut/46842f93171d_device13",
    "_to": "Location/46842f93171d_location1",
    "created": 1757725696.949194,
    "expired": 9223372036854775807,
    "tenant_46842f93171d_attr": "46842f93171d",
    "_fromType": "DeviceProxyOut",
    "_toType": "Location"
  },
  {
    "_key": "46842f93171d_hasLocation14",
    "_from": "DeviceProxyOut/46842f93171d_device14",
    "_to": "Location/46842f93171d_location5",
    "created": 1757725696.949196,
    "expired": 9223372036854775807,
    "tenant_46842f93171d_attr": "46842f93171d",
    "_fromType": "DeviceProxyOut",
    "_toType": "Location"
  },
  {
    "_key": "46842f93171d_hasLocation15",
    "_from": "DeviceProxyOut/46842f93171d_device15",
    "_to": "Location/46842f93171d_location2",
    "created": 1757725696.949198,
    "expired": 9223372036854775807,
    "tenant_46842f93171d_attr": "46842f93171d",
    "_fromType": "DeviceProxyOut",
    "_toType": "Location"
  },
  {
    "_key": "46842f93171d_hasLocation16",
    "_from": "DeviceProxyOut/46842f93171d_device16",
    "_to": "Location/46842f93171d_location8",
    "created": 1757725696.9492,
    "expired": 9223372036854775807,
    "tenant_46842f93171d_attr": "46842f93171d",
    "_fromType": "DeviceProxyOut",
    "_toType": "Location"
  },
  {
    "_key": "46842f93171d_hasLocation17",
    "_from": "DeviceProxyOut/46842f93171d_device17",
    "_to": "Location/46842f93171d_location5",
    "created": 1757725696.949203,
    "expired": 9223372036854775807,
    "tenant_46842f93171d_attr": "46842f93171d",
    "_fromType": "DeviceProxyOut",
    "_toType": "Location"
  },
  {
    "_key": "46842f93171d_hasLocation18",
    "_from": "DeviceProxyOut/46842f93171d_device18",
    "_to": "Location/46842f93171d_location6",
    "created": 1757725696.949205,
    "expired": 9223372036854775807,
    "tenant_46842f93171d_attr": "46842f93171d",
    "_fromType": "DeviceProxyOut",
    "_toType": "Location"
  },
  {
    "_key": "46842f93171d_hasLocation19",
    "_from": "DeviceProxyOut/46842f93171d_device19",
    "_to": "Location/46842f93171d_location10",
    "created": 1757725696.949207,
    "expired": 9223372036854775807,
    "tenant_46842f93171d_attr": "46842f93171d",
    "_fromType": "DeviceProxyOut",
    "_toType": "Location"
  },
  {
    "_key": "46842f93171d_hasLocation20",
    "_from": "DeviceProxyOut/46842f93171d_device20",
    "_to": "Location/46842f93171d_location3",
    "created": 1757725696.949209,
    "expired": 9223372036854775807,
    "tenant_46842f93171d_attr": "46842f93171d",
    "_fromType": "DeviceProxyOut",
    "_toType": "Location"
  },
  {
    "_key": "46842f93171d_hasLocation21",
    "_from": "DeviceProxyOut/46842f93171d_device21",
    "_to": "Location/46842f93171d_location10",
    "created": 1757725696.949214,
    "expired": 9223372036854775807,
    "tenant_46842f93171d_attr": "46842f93171d",
    "_fromType": "DeviceProxyOut",
    "_toType": "Location"
  },
  {
    "_key": "46842f93171d_hasLocation22",
    "_from": "DeviceProxyOut/46842f93171d_device22",
    "_to": "Location/46842f93171d_location9",
    "created": 1757725696.949216,
    "expired": 9223372036854775807,
    "tenant_46842f93171d_attr": "46842f93171d",
    "_fromType": "DeviceProxyOut",
    "_toType": "Location"
  },
  {
    "_key": "46842f93171d_hasLocation23",
    "_from": "DeviceProxyOut/46842f93171d_device23",
    "_to": "Location/46842f93171d_location4",
    "created": 1757725696.949218,
    "expired": 9223372036854775807,
    "tenant_46842f93171d_attr": "46842f93171d",
    "_fromType": "DeviceProxyOut",
    "_toType": "Location"
  },
  {
    "_key": "46842f93171d_hasLocation24",
    "_from": "DeviceProxyOut/46842f93171d_device24",
    "_to": "Location/46842f93171d_location1",
    "created": 1757725696.94922,
    "expired": 9223372036854775807,
    "tenant_46842f93171d_attr": "46842f93171d",
    "_fromType": "DeviceProxyOut",
    "_toType": "Location"
  },
  {
    "_key": "46842f93171d_hasLocation25",
    "_from": "DeviceProxyOut/46842f93171d_device25",
    "_to": "Location/46842f93171d_location6",
    "created": 1757725696.949222,
    "expired": 9223372036854775807,
    "tenant_46842f93171d_attr": "46842f93171d",
    "_fromType": "DeviceProxyOut",
    "_toType": "Location"
  },
  {
    "_key": "46842f93171d_hasLocation26",
    "_from": "DeviceProxyOut/46842f93171d_device26",
    "_to": "Location/46842f93171d_location8",
    "created": 1757725696.949225,
    "expired": 9223372036854775807,
    "tenant_46842f93171d_attr": "46842f93171d",
    "_fromType": "DeviceProxyOut",
    "_toType": "Location"
  },
  {
    "_key": "46842f93171d_hasLocation27",
    "_from": "DeviceProxyOut/46842f93171d_device27",
    "_to": "Location/46842f93171d_location1",
    "created": 1757725696.949227,
    "expired": 9223372036854775807,
    "tenant_46842f93171d_attr": "46842f93171d",
    "_fromType": "DeviceProxyOut",
    "_toType": "Location"
  },
  {
    "_key": "46842f93171d_hasLocation28",
    "_from": "DeviceProxyOut/46842f93171d_device28",
    "_to": "Location/46842f93171d_location5",
    "created": 1757725696.949229,
    "expired": 9223372036854775807,
    "tenant_46842f93171d_attr": "46842f93171d",
    "_fromType": "DeviceProxyOut",
    "_toType": "Location"
  },
  {
    "_key": "46842f93171d_hasLocation29",
    "_from": "DeviceProxyOut/46842f93171d_device29",
    "_to": "Location/46842f93171d_location3",
    "created": 1757725696.949231,
    "expired": 9223372036854775807,
    "tenant_46842f93171d_attr": "46842f93171d",
    "_fromType": "DeviceProxyOut",
    "_toType": "Location"
  },
  {
    "_key": "46842f93171d_hasLocation30",
    "_from": "DeviceProxyOut/46842f93171d_device30",
    "_to": "Location/46842f93171d_location4",
    "created": 1757725696.949233,
    "expired": 9223372036854775807,
    "tenant_46842f93171d_attr": "46842f93171d",
    "_fromType": "DeviceProxyOut",
    "_toType": "Location"
  },
  {
    "_key": "46842f93171d_hasLocation31",
    "_from": "DeviceProxyOut/46842f93171d_device31",
    "_to": "Location/46842f93171d_location2",
    "created": 1757725696.949235,
    "expired": 9223372036854775807,
    "tenant_46842f93171d_attr": "46842f93171d",
    "_fromType": "DeviceProxyOut",
    "_toType": "Location"
  },
  {
    "_key": "46842f93171d_hasLocation32",
    "_from": "DeviceProxyOut/46842f93171d_device32",
    "_to": "Location/46842f93171d_location10",
    "created": 1757725696.949237,
    "expired": 9223372036854775807,
    "tenant_46842f93171d_attr": "46842f93171d",
    "_fromType": "DeviceProxyOut",
    "_toType": "Location"
  },
  {
    "_key": "46842f93171d_hasLocation33",
    "_from": "DeviceProxyOut/46842f93171d_device33",
    "_to": "Location/46842f93171d_location8",
    "created": 1757725696.949239,
    "expired": 9223372036854775807,
    "tenant_46842f93171d_attr": "46842f93171d",
    "_fromType": "DeviceProxyOut",
    "_toType": "Location"
  },
  {
    "_key": "46842f93171d_hasLocation34",
    "_from": "DeviceProxyOut/46842f93171d_device34",
    "_to": "Location/46842f93171d_location3",
    "created": 1757725696.949242,
    "expired": 9223372036854775807,
    "tenant_46842f93171d_attr": "46842f93171d",
    "_fromType": "DeviceProxyOut",
    "_toType": "Location"
  },
  {
    "_key": "46842f93171d_hasLocation35",
    "_from": "DeviceProxyOut/46842f93171d_device35",
    "_to": "Location/46842f93171d_location4",
    "created": 1757725696.949244,
    "expired": 9223372036854775807,
    "tenant_46842f93171d_attr": "46842f93171d",
    "_fromType": "DeviceProxyOut",
    "_toType": "Location"
  },
  {
    "_key": "46842f93171d_hasLocation36",
    "_from": "DeviceProxyOut/46842f93171d_device36",
    "_to": "Location/46842f93171d_location4",
    "created": 1757725696.949246,
    "expired": 9223372036854775807,
    "tenant_46842f93171d_attr": "46842f93171d",
    "_fromType": "DeviceProxyOut",
    "_toType": "Location"
  },
  {
    "_key": "46842f93171d_hasLocation37",
    "_from": "DeviceProxyOut/46842f93171d_device37",
    "_to": "Location/46842f93171d_location7",
    "created": 1757725696.949248,
    "expired": 9223372036854775807,
    "tenant_46842f93171d_attr": "46842f93171d",
    "_fromType": "DeviceProxyOut",
    "_toType": "Location"
  },
  {
    "_key": "46842f93171d_hasLocation38",
    "_from": "DeviceProxyOut/46842f93171d_device38",
    "_to": "Location/46842f93171d_location2",
    "created": 1757725696.94925,
    "expired": 9223372036854775807,
    "tenant_46842f93171d_attr": "46842f93171d",
    "_fromType": "DeviceProxyOut",
    "_toType": "Location"
  },
  {
    "_key": "46842f93171d_hasLocation39",
    "_from": "DeviceProxyOut/46842f93171d_device39",
    "_to": "Location/46842f93171d_location1",
    "created": 1757725696.949252,
    "expired": 9223372036854775807,
    "tenant_46842f93171d_attr": "46842f93171d",
    "_fromType": "DeviceProxyOut",
    "_toType": "Location"
  },
  {
    "_key": "46842f93171d_hasLocation40",
    "_from": "DeviceProxyOut/46842f93171d_device40",
    "_to": "Location/46842f93171d_location6",
    "created": 1757725696.949254,
    "expired": 9223372036854775807,
    "tenant_46842f93171d_attr": "46842f93171d",
    "_fromType": "DeviceProxyOut",
    "_toType": "Location"
  }
]