[
  {
    "_key": "41cd677709e6_hasSoftware1",
    "_from": "DeviceProxyOut/41cd677709e6_device11",
    "_to": "SoftwareProxyIn/41cd677709e6_software1",
    "created": 1757903278.624885,
    "expired": 9223372036854775807,
    "tenant_41cd677709e6_attr": "41cd677709e6",
    "_fromType": "DeviceProxyOut",
    "_toType": "SoftwareProxyIn"
  },
  {
    "_key": "41cd677709e6_hasSoftware2",
    "_from": "DeviceProxyOut/41cd677709e6_device1",
    "_to": "SoftwareProxyIn/41cd677709e6_software2",
    "created": 1757903278.624889,
    "expired": 9223372036854775807,
    "tenant_41cd677709e6_attr": "41cd677709e6",
    "_fromType": "DeviceProxyOut",
    "_toType": "SoftwareProxyIn"
  },
  {
    "_key": "41cd677709e6_hasSoftware3",
    "_from": "DeviceProxyOut/41cd677709e6_device1",
    "_to": "SoftwareProxyIn/41cd677709e6_software3",
    "created": 1757903278.624892,
    "expired": 9223372036854775807,
    "tenant_41cd677709e6_attr": "41cd677709e6",
    "_fromType": "DeviceProxyOut",
    "_toType": "SoftwareProxyIn"
  },
  {
    "_key": "41cd677709e6_hasSoftware4",
    "_from": "DeviceProxyOut/41cd677709e6_device17",
    "_to": "SoftwareProxyIn/41cd677709e6_software4",
    "created": 1757903278.624895,
    "expired": 9223372036854775807,
    "tenant_41cd677709e6_attr": "41cd677709e6",
    "_fromType": "DeviceProxyOut",
    "_toType": "SoftwareProxyIn"
  },
  {
    "_key": "41cd677709e6_hasSoftware5",
    "_from": "DeviceProxyOut/41cd677709e6_device17",
    "_to": "SoftwareProxyIn/41cd677709e6_software5",
    "created": 1757903278.624897,
    "expired": 9223372036854775807,
    "tenant_41cd677709e6_attr": "41cd677709e6",
    "_fromType": "DeviceProxyOut",
    "_toType": "SoftwareProxyIn"
  },
  {
    "_key": "41cd677709e6_hasSoftware6",
    "_from": "DeviceProxyOut/41cd677709e6_device24",
    "_to": "SoftwareProxyIn/41cd677709e6_software6",
    "created": 1757903278.6249,
    "expired": 9223372036854775807,
    "tenant_41cd677709e6_attr": "41cd677709e6",
    "_fromType": "DeviceProxyOut",
    "_toType": "SoftwareProxyIn"
  },
  {
    "_key": "41cd677709e6_hasSoftware7",
    "_from": "DeviceProxyOut/41cd677709e6_device15",
    "_to": "SoftwareProxyIn/41cd677709e6_software7",
    "created": 1757903278.624902,
    "expired": 9223372036854775807,
    "tenant_41cd677709e6_attr": "41cd677709e6",
    "_fromType": "DeviceProxyOut",
    "_toType": "SoftwareProxyIn"
  },
  {
    "_key": "41cd677709e6_hasSoftware8",
    "_from": "DeviceProxyOut/41cd677709e6_device34",
    "_to": "SoftwareProxyIn/41cd677709e6_software8",
    "created": 1757903278.624904,
    "expired": 9223372036854775807,
    "tenant_41cd677709e6_attr": "41cd677709e6",
    "_fromType": "DeviceProxyOut",
    "_toType": "SoftwareProxyIn"
  },
  {
    "_key": "41cd677709e6_hasSoftware9",
    "_from": "DeviceProxyOut/41cd677709e6_device21",
    "_to": "SoftwareProxyIn/41cd677709e6_software9",
    "created": 1757903278.624906,
    "expired": 9223372036854775807,
    "tenant_41cd677709e6_attr": "41cd677709e6",
    "_fromType": "DeviceProxyOut",
    "_toType": "SoftwareProxyIn"
  },
  {
    "_key": "41cd677709e6_hasSoftware10",
    "_from": "DeviceProxyOut/41cd677709e6_device25",
    "_to": "SoftwareProxyIn/41cd677709e6_software10",
    "created": 1757903278.624909,
    "expired": 9223372036854775807,
    "tenant_41cd677709e6_attr": "41cd677709e6",
    "_fromType": "DeviceProxyOut",
    "_toType": "SoftwareProxyIn"
  },
  {
    "_key": "41cd677709e6_hasSoftware11",
    "_from": "DeviceProxyOut/41cd677709e6_device37",
    "_to": "SoftwareProxyIn/41cd677709e6_software11",
    "created": 1757903278.624911,
    "expired": 9223372036854775807,
    "tenant_41cd677709e6_attr": "41cd677709e6",
    "_fromType": "DeviceProxyOut",
    "_toType": "SoftwareProxyIn"
  },
  {
    "_key": "41cd677709e6_hasSoftware12",
    "_from": "DeviceProxyOut/41cd677709e6_device11",
    "_to": "SoftwareProxyIn/41cd677709e6_software12",
    "created": 1757903278.624913,
    "expired": 9223372036854775807,
    "tenant_41cd677709e6_attr": "41cd677709e6",
    "_fromType": "DeviceProxyOut",
    "_toType": "SoftwareProxyIn"
  },
  {
    "_key": "41cd677709e6_hasSoftware13",
    "_from": "DeviceProxyOut/41cd677709e6_device5",
    "_to": "SoftwareProxyIn/41cd677709e6_software13",
    "created": 1757903278.624916,
    "expired": 9223372036854775807,
    "tenant_41cd677709e6_attr": "41cd677709e6",
    "_fromType": "DeviceProxyOut",
    "_toType": "SoftwareProxyIn"
  },
  {
    "_key": "41cd677709e6_hasSoftware14",
    "_from": "DeviceProxyOut/41cd677709e6_device18",
    "_to": "SoftwareProxyIn/41cd677709e6_software14",
    "created": 1757903278.624918,
    "expired": 9223372036854775807,
    "tenant_41cd677709e6_attr": "41cd677709e6",
    "_fromType": "DeviceProxyOut",
    "_toType": "SoftwareProxyIn"
  },
  {
    "_key": "41cd677709e6_hasSoftware15",
    "_from": "DeviceProxyOut/41cd677709e6_device6",
    "_to": "SoftwareProxyIn/41cd677709e6_software15",
    "created": 1757903278.62492,
    "expired": 9223372036854775807,
    "tenant_41cd677709e6_attr": "41cd677709e6",
    "_fromType": "DeviceProxyOut",
    "_toType": "SoftwareProxyIn"
  },
  {
    "_key": "41cd677709e6_hasSoftware16",
    "_from": "DeviceProxyOut/41cd677709e6_device5",
    "_to": "SoftwareProxyIn/41cd677709e6_software16",
    "created": 1757903278.624924,
    "expired": 9223372036854775807,
    "tenant_41cd677709e6_attr": "41cd677709e6",
    "_fromType": "DeviceProxyOut",
    "_toType": "SoftwareProxyIn"
  },
  {
    "_key": "41cd677709e6_hasSoftware17",
    "_from": "DeviceProxyOut/41cd677709e6_device5",
    "_to": "SoftwareProxyIn/41cd677709e6_software17",
    "created": 1757903278.624926,
    "expired": 9223372036854775807,
    "tenant_41cd677709e6_attr": "41cd677709e6",
    "_fromType": "DeviceProxyOut",
    "_toType": "SoftwareProxyIn"
  },
  {
    "_key": "41cd677709e6_hasSoftware18",
    "_from": "DeviceProxyOut/41cd677709e6_device29",
    "_to": "SoftwareProxyIn/41cd677709e6_software18",
    "created": 1757903278.624929,
    "expired": 9223372036854775807,
    "tenant_41cd677709e6_attr": "41cd677709e6",
    "_fromType": "DeviceProxyOut",
    "_toType": "SoftwareProxyIn"
  },
  {
    "_key": "41cd677709e6_hasSoftware19",
    "_from": "DeviceProxyOut/41cd677709e6_device24",
    "_to": "SoftwareProxyIn/41cd677709e6_software19",
    "created": 1757903278.624931,
    "expired": 9223372036854775807,
    "tenant_41cd677709e6_attr": "41cd677709e6",
    "_fromType": "DeviceProxyOut",
    "_toType": "SoftwareProxyIn"
  },
  {
    "_key": "41cd677709e6_hasSoftware20",
    "_from": "DeviceProxyOut/41cd677709e6_device34",
    "_to": "SoftwareProxyIn/41cd677709e6_software20",
    "created": 1757903278.624934,
    "expired": 9223372036854775807,
    "tenant_41cd677709e6_attr": "41cd677709e6",
    "_fromType": "DeviceProxyOut",
    "_toType": "SoftwareProxyIn"
  },
  {
    "_key": "41cd677709e6_hasSoftware21",
    "_from": "DeviceProxyOut/41cd677709e6_device9",
    "_to": "SoftwareProxyIn/41cd677709e6_software21",
    "created": 1757903278.624936,
    "expired": 9223372036854775807,
    "tenant_41cd677709e6_attr": "41cd677709e6",
    "_fromType": "DeviceProxyOut",
    "_toType": "SoftwareProxyIn"
  },
  {
    "_key": "41cd677709e6_hasSoftware22",
    "_from": "DeviceProxyOut/41cd677709e6_device31",
    "_to": "SoftwareProxyIn/41cd677709e6_software22",
    "created": 1757903278.624938,
    "expired": 9223372036854775807,
    "tenant_41cd677709e6_attr": "41cd677709e6",
    "_fromType": "DeviceProxyOut",
    "_toType": "SoftwareProxyIn"
  },
  {
    "_key": "41cd677709e6_hasSoftware23",
    "_from": "DeviceProxyOut/41cd677709e6_device19",
    "_to": "SoftwareProxyIn/41cd677709e6_software23",
    "created": 1757903278.62494,
    "expired": 9223372036854775807,
    "tenant_41cd677709e6_attr": "41cd677709e6",
    "_fromType": "DeviceProxyOut",
    "_toType": "SoftwareProxyIn"
  },
  {
    "_key": "41cd677709e6_hasSoftware24",
    "_from": "DeviceProxyOut/41cd677709e6_device10",
    "_to": "SoftwareProxyIn/41cd677709e6_software24",
    "created": 1757903278.624942,
    "expired": 9223372036854775807,
    "tenant_41cd677709e6_attr": "41cd677709e6",
    "_fromType": "DeviceProxyOut",
    "_toType": "SoftwareProxyIn"
  },
  {
    "_key": "41cd677709e6_hasSoftware25",
    "_from": "DeviceProxyOut/41cd677709e6_device16",
    "_to": "SoftwareProxyIn/41cd677709e6_software25",
    "created": 1757903278.624945,
    "expired": 9223372036854775807,
    "tenant_41cd677709e6_attr": "41cd677709e6",
    "_fromType": "DeviceProxyOut",
    "_toType": "SoftwareProxyIn"
  },
  {
    "_key": "41cd677709e6_hasSoftware26",
    "_from": "DeviceProxyOut/41cd677709e6_device9",
    "_to": "SoftwareProxyIn/41cd677709e6_software26",
    "created": 1757903278.624947,
    "expired": 9223372036854775807,
    "tenant_41cd677709e6_attr": "41cd677709e6",
    "_fromType": "DeviceProxyOut",
    "_toType": "SoftwareProxyIn"
  },
  {
    "_key": "41cd677709e6_hasSoftware27",
    "_from": "DeviceProxyOut/41cd677709e6_device33",
    "_to": "SoftwareProxyIn/41cd677709e6_software27",
    "created": 1757903278.624949,
    "expired": 9223372036854775807,
    "tenant_41cd677709e6_attr": "41cd677709e6",
    "_fromType": "DeviceProxyOut",
    "_toType": "SoftwareProxyIn"
  },
  {
    "_key": "41cd677709e6_hasSoftware28",
    "_from": "DeviceProxyOut/41cd677709e6_device19",
    "_to": "SoftwareProxyIn/41cd677709e6_software28",
    "created": 1757903278.624951,
    "expired": 9223372036854775807,
    "tenant_41cd677709e6_attr": "41cd677709e6",
    "_fromType": "DeviceProxyOut",
    "_toType": "SoftwareProxyIn"
  },
  {
    "_key": "41cd677709e6_hasSoftware29",
    "_from": "DeviceProxyOut/41cd677709e6_device12",
    "_to": "SoftwareProxyIn/41cd677709e6_software29",
    "created": 1757903278.624954,
    "expired": 9223372036854775807,
    "tenant_41cd677709e6_attr": "41cd677709e6",
    "_fromType": "DeviceProxyOut",
    "_toType": "SoftwareProxyIn"
  },
  {
    "_key": "41cd677709e6_hasSoftware30",
    "_from": "DeviceProxyOut/41cd677709e6_device25",
    "_to": "SoftwareProxyIn/41cd677709e6_software30",
    "created": 1757903278.624956,
    "expired": 9223372036854775807,
    "tenant_41cd677709e6_attr": "41cd677709e6",
    "_fromType": "DeviceProxyOut",
    "_toType": "SoftwareProxyIn"
  },
  {
    "_key": "41cd677709e6_hasSoftware31",
    "_from": "DeviceProxyOut/41cd677709e6_device39",
    "_to": "SoftwareProxyIn/41cd677709e6_software31",
    "created": 1757903278.624958,
    "expired": 9223372036854775807,
    "tenant_41cd677709e6_attr": "41cd677709e6",
    "_fromType": "DeviceProxyOut",
    "_toType": "SoftwareProxyIn"
  },
  {
    "_key": "41cd677709e6_hasSoftware32",
    "_from": "DeviceProxyOut/41cd677709e6_device9",
    "_to": "SoftwareProxyIn/41cd677709e6_software32",
    "created": 1757903278.624961,
    "expired": 9223372036854775807,
    "tenant_41cd677709e6_attr": "41cd677709e6",
    "_fromType": "DeviceProxyOut",
    "_toType": "SoftwareProxyIn"
  },
  {
    "_key": "41cd677709e6_hasSoftware33",
    "_from": "DeviceProxyOut/41cd677709e6_device12",
    "_to": "SoftwareProxyIn/41cd677709e6_software33",
    "created": 1757903278.624963,
    "expired": 9223372036854775807,
    "tenant_41cd677709e6_attr": "41cd677709e6",
    "_fromType": "DeviceProxyOut",
    "_toType": "SoftwareProxyIn"
  },
  {
    "_key": "41cd677709e6_hasSoftware34",
    "_from": "DeviceProxyOut/41cd677709e6_device37",
    "_to": "SoftwareProxyIn/41cd677709e6_software34",
    "created": 1757903278.624966,
    "expired": 9223372036854775807,
    "tenant_41cd677709e6_attr": "41cd677709e6",
    "_fromType": "DeviceProxyOut",
    "_toType": "SoftwareProxyIn"
  },
  {
    "_key": "41cd677709e6_hasSoftware35",
    "_from": "DeviceProxyOut/41cd677709e6_device16",
    "_to": "SoftwareProxyIn/41cd677709e6_software35",
    "created": 1757903278.624969,
    "expired": 9223372036854775807,
    "tenant_41cd677709e6_attr": "41cd677709e6",
    "_fromType": "DeviceProxyOut",
    "_toType": "SoftwareProxyIn"
  },
  {
    "_key": "41cd677709e6_hasSoftware36",
    "_from": "DeviceProxyOut/41cd677709e6_device11",
    "_to": "SoftwareProxyIn/41cd677709e6_software36",
    "created": 1757903278.624971,
    "expired": 9223372036854775807,
    "tenant_41cd677709e6_attr": "41cd677709e6",
    "_fromType": "DeviceProxyOut",
    "_toType": "SoftwareProxyIn"
  },
  {
    "_key": "41cd677709e6_hasSoftware37",
    "_from": "DeviceProxyOut/41cd677709e6_device28",
    "_to": "SoftwareProxyIn/41cd677709e6_software37",
    "created": 1757903278.624973,
    "expired": 9223372036854775807,
    "tenant_41cd677709e6_attr": "41cd677709e6",
    "_fromType": "DeviceProxyOut",
    "_toType": "SoftwareProxyIn"
  },
  {
    "_key": "41cd677709e6_hasSoftware38",
    "_from": "DeviceProxyOut/41cd677709e6_device6",
    "_to": "SoftwareProxyIn/41cd677709e6_software38",
    "created": 1757903278.624975,
    "expired": 9223372036854775807,
    "tenant_41cd677709e6_attr": "41cd677709e6",
    "_fromType": "DeviceProxyOut",
    "_toType": "SoftwareProxyIn"
  },
  {
    "_key": "41cd677709e6_hasSoftware39",
    "_from": "DeviceProxyOut/41cd677709e6_device37",
    "_to": "SoftwareProxyIn/41cd677709e6_software39",
    "created": 1757903278.624977,
    "expired": 9223372036854775807,
    "tenant_41cd677709e6_attr": "41cd677709e6",
    "_fromType": "DeviceProxyOut",
    "_toType": "SoftwareProxyIn"
  },
  {
    "_key": "41cd677709e6_hasSoftware40",
    "_from": "DeviceProxyOut/41cd677709e6_device18",
    "_to": "SoftwareProxyIn/41cd677709e6_software40",
    "created": 1757903278.62498,
    "expired": 9223372036854775807,
    "tenant_41cd677709e6_attr": "41cd677709e6",
    "_fromType": "DeviceProxyOut",
    "_toType": "SoftwareProxyIn"
  },
  {
    "_key": "41cd677709e6_hasSoftware41",
    "_from": "DeviceProxyOut/41cd677709e6_device37",
    "_to": "SoftwareProxyIn/41cd677709e6_software41",
    "created": 1757903278.624982,
    "expired": 9223372036854775807,
    "tenant_41cd677709e6_attr": "41cd677709e6",
    "_fromType": "DeviceProxyOut",
    "_toType": "SoftwareProxyIn"
  },
  {
    "_key": "41cd677709e6_hasSoftware42",
    "_from": "DeviceProxyOut/41cd677709e6_device37",
    "_to": "SoftwareProxyIn/41cd677709e6_software42",
    "created": 1757903278.624984,
    "expired": 9223372036854775807,
    "tenant_41cd677709e6_attr": "41cd677709e6",
    "_fromType": "DeviceProxyOut",
    "_toType": "SoftwareProxyIn"
  },
  {
    "_key": "41cd677709e6_hasSoftware43",
    "_from": "DeviceProxyOut/41cd677709e6_device27",
    "_to": "SoftwareProxyIn/41cd677709e6_software43",
    "created": 1757903278.624987,
    "expired": 9223372036854775807,
    "tenant_41cd677709e6_attr": "41cd677709e6",
    "_fromType": "DeviceProxyOut",
    "_toType": "SoftwareProxyIn"
  },
  {
    "_key": "41cd677709e6_hasSoftware44",
    "_from": "DeviceProxyOut/41cd677709e6_device27",
    "_to": "SoftwareProxyIn/41cd677709e6_software44",
    "created": 1757903278.624991,
    "expired": 9223372036854775807,
    "tenant_41cd677709e6_attr": "41cd677709e6",
    "_fromType": "DeviceProxyOut",
    "_toType": "SoftwareProxyIn"
  },
  {
    "_key": "41cd677709e6_hasSoftware45",
    "_from": "DeviceProxyOut/41cd677709e6_device7",
    "_to": "SoftwareProxyIn/41cd677709e6_software45",
    "created": 1757903278.624993,
    "expired": 9223372036854775807,
    "tenant_41cd677709e6_attr": "41cd677709e6",
    "_fromType": "DeviceProxyOut",
    "_toType": "SoftwareProxyIn"
  },
  {
    "_key": "41cd677709e6_hasSoftware46",
    "_from": "DeviceProxyOut/41cd677709e6_device5",
    "_to": "SoftwareProxyIn/41cd677709e6_software46",
    "created": 1757903278.624995,
    "expired": 9223372036854775807,
    "tenant_41cd677709e6_attr": "41cd677709e6",
    "_fromType": "DeviceProxyOut",
    "_toType": "SoftwareProxyIn"
  },
  {
    "_key": "41cd677709e6_hasSoftware47",
    "_from": "DeviceProxyOut/41cd677709e6_device2",
    "_to": "SoftwareProxyIn/41cd677709e6_software47",
    "created": 1757903278.624998,
    "expired": 9223372036854775807,
    "tenant_41cd677709e6_attr": "41cd677709e6",
    "_fromType": "DeviceProxyOut",
    "_toType": "SoftwareProxyIn"
  },
  {
    "_key": "41cd677709e6_hasSoftware48",
    "_from": "DeviceProxyOut/41cd677709e6_device6",
    "_to": "SoftwareProxyIn/41cd677709e6_software48",
    "created": 1757903278.625,
    "expired": 9223372036854775807,
    "tenant_41cd677709e6_attr": "41cd677709e6",
    "_fromType": "DeviceProxyOut",
    "_toType": "SoftwareProxyIn"
  },
  {
    "_key": "41cd677709e6_hasSoftware49",
    "_from": "DeviceProxyOut/41cd677709e6_device8",
    "_to": "SoftwareProxyIn/41cd677709e6_software49",
    "created": 1757903278.625002,
    "expired": 9223372036854775807,
    "tenant_41cd677709e6_attr": "41cd677709e6",
    "_fromType": "DeviceProxyOut",
    "_toType": "SoftwareProxyIn"
  },
  {
    "_key": "41cd677709e6_hasSoftware50",
    "_from": "DeviceProxyOut/41cd677709e6_device28",
    "_to": "SoftwareProxyIn/41cd677709e6_software50",
    "created": 1757903278.625004,
    "expired": 9223372036854775807,
    "tenant_41cd677709e6_attr": "41cd677709e6",
    "_fromType": "DeviceProxyOut",
    "_toType": "SoftwareProxyIn"
  },
  {
    "_key": "41cd677709e6_hasSoftware51",
    "_from": "DeviceProxyOut/41cd677709e6_device23",
    "_to": "SoftwareProxyIn/41cd677709e6_software51",
    "created": 1757903278.625007,
    "expired": 9223372036854775807,
    "tenant_41cd677709e6_attr": "41cd677709e6",
    "_fromType": "DeviceProxyOut",
    "_toType": "SoftwareProxyIn"
  },
  {
    "_key": "41cd677709e6_hasSoftware52",
    "_from": "DeviceProxyOut/41cd677709e6_device23",
    "_to": "SoftwareProxyIn/41cd677709e6_software52",
    "created": 1757903278.625009,
    "expired": 9223372036854775807,
    "tenant_41cd677709e6_attr": "41cd677709e6",
    "_fromType": "DeviceProxyOut",
    "_toType": "SoftwareProxyIn"
  },
  {
    "_key": "41cd677709e6_hasSoftware53",
    "_from": "DeviceProxyOut/41cd677709e6_device39",
    "_to": "SoftwareProxyIn/41cd677709e6_software53",
    "created": 1757903278.625011,
    "expired": 9223372036854775807,
    "tenant_41cd677709e6_attr": "41cd677709e6",
    "_fromType": "DeviceProxyOut",
    "_toType": "SoftwareProxyIn"
  },
  {
    "_key": "41cd677709e6_hasSoftware54",
    "_from": "DeviceProxyOut/41cd677709e6_device30",
    "_to": "SoftwareProxyIn/41cd677709e6_software54",
    "created": 1757903278.625013,
    "expired": 9223372036854775807,
    "tenant_41cd677709e6_attr": "41cd677709e6",
    "_fromType": "DeviceProxyOut",
    "_toType": "SoftwareProxyIn"
  },
  {
    "_key": "41cd677709e6_hasSoftware55",
    "_from": "DeviceProxyOut/41cd677709e6_device34",
    "_to": "SoftwareProxyIn/41cd677709e6_software55",
    "created": 1757903278.625016,
    "expired": 9223372036854775807,
    "tenant_41cd677709e6_attr": "41cd677709e6",
    "_fromType": "DeviceProxyOut",
    "_toType": "SoftwareProxyIn"
  },
  {
    "_key": "41cd677709e6_hasSoftware56",
    "_from": "DeviceProxyOut/41cd677709e6_device9",
    "_to": "SoftwareProxyIn/41cd677709e6_software56",
    "created": 1757903278.625018,
    "expired": 9223372036854775807,
    "tenant_41cd677709e6_attr": "41cd677709e6",
    "_fromType": "DeviceProxyOut",
    "_toType": "SoftwareProxyIn"
  },
  {
    "_key": "41cd677709e6_hasSoftware57",
    "_from": "DeviceProxyOut/41cd677709e6_device18",
    "_to": "SoftwareProxyIn/41cd677709e6_software57",
    "created": 1757903278.62502,
    "expired": 9223372036854775807,
    "tenant_41cd677709e6_attr": "41cd677709e6",
    "_fromType": "DeviceProxyOut",
    "_toType": "SoftwareProxyIn"
  },
  {
    "_key": "41cd677709e6_hasSoftware58",
    "_from": "DeviceProxyOut/41cd677709e6_device31",
    "_to": "SoftwareProxyIn/41cd677709e6_software58",
    "created": 1757903278.625022,
    "expired": 9223372036854775807,
    "tenant_41cd677709e6_attr": "41cd677709e6",
    "_fromType": "DeviceProxyOut",
    "_toType": "SoftwareProxyIn"
  },
  {
    "_key": "41cd677709e6_hasSoftware59",
    "_from": "DeviceProxyOut/41cd677709e6_device27",
    "_to": "SoftwareProxyIn/41cd677709e6_software59",
    "created": 1757903278.625024,
    "expired": 9223372036854775807,
    "tenant_41cd677709e6_attr": "41cd677709e6",
    "_fromType": "DeviceProxyOut",
    "_toType": "SoftwareProxyIn"
  },
  {
    "_key": "41cd677709e6_hasSoftware60",
    "_from": "DeviceProxyOut/41cd677709e6_device39",
    "_to": "SoftwareProxyIn/41cd677709e6_software60",
    "created": 1757903278.625027,
    "expired": 9223372036854775807,
    "tenant_41cd677709e6_attr": "41cd677709e6",
    "_fromType": "DeviceProxyOut",
    "_toType": "SoftwareProxyIn"
  },
  {
    "_key": "41cd677709e6_hasSoftware61",
    "_from": "DeviceProxyOut/41cd677709e6_device22",
    "_to": "SoftwareProxyIn/41cd677709e6_software48",
    "created": 1757903278.625053,
    "expired": 9223372036854775807,
    "tenant_41cd677709e6_attr": "41cd677709e6",
    "_fromType": "DeviceProxyOut",
    "_toType": "SoftwareProxyIn"
  },
  {
    "_key": "41cd677709e6_hasSoftware62",
    "_from": "DeviceProxyOut/41cd677709e6_device8",
    "_to": "SoftwareProxyIn/41cd677709e6_software5",
    "created": 1757903278.625074,
    "expired": 9223372036854775807,
    "tenant_41cd677709e6_attr": "41cd677709e6",
    "_fromType": "DeviceProxyOut",
    "_toType": "SoftwareProxyIn"
  },
  {
    "_key": "41cd677709e6_hasSoftware63",
    "_from": "DeviceProxyOut/41cd677709e6_device37",
    "_to": "SoftwareProxyIn/41cd677709e6_software22",
    "created": 1757903278.625093,
    "expired": 9223372036854775807,
    "tenant_41cd677709e6_attr": "41cd677709e6",
    "_fromType": "DeviceProxyOut",
    "_toType": "SoftwareProxyIn"
  },
  {
    "_key": "41cd677709e6_hasSoftware64",
    "_from": "DeviceProxyOut/41cd677709e6_device39",
    "_to": "SoftwareProxyIn/41cd677709e6_software55",
    "created": 1757903278.625113,
    "expired": 9223372036854775807,
    "tenant_41cd677709e6_attr": "41cd677709e6",
    "_fromType": "DeviceProxyOut",
    "_toType": "SoftwareProxyIn"
  },
  {
    "_key": "41cd677709e6_hasSoftware65",
    "_from": "DeviceProxyOut/41cd677709e6_device25",
    "_to": "SoftwareProxyIn/41cd677709e6_software1",
    "created": 1757903278.625132,
    "expired": 9223372036854775807,
    "tenant_41cd677709e6_attr": "41cd677709e6",
    "_fromType": "DeviceProxyOut",
    "_toType": "SoftwareProxyIn"
  },
  {
    "_key": "41cd677709e6_hasSoftware66",
    "_from": "DeviceProxyOut/41cd677709e6_device5",
    "_to": "SoftwareProxyIn/41cd677709e6_software31",
    "created": 1757903278.625153,
    "expired": 9223372036854775807,
    "tenant_41cd677709e6_attr": "41cd677709e6",
    "_fromType": "DeviceProxyOut",
    "_toType": "SoftwareProxyIn"
  },
  {
    "_key": "41cd677709e6_hasSoftware67",
    "_from": "DeviceProxyOut/41cd677709e6_device28",
    "_to": "SoftwareProxyIn/41cd677709e6_software54",
    "created": 1757903278.625173,
    "expired": 9223372036854775807,
    "tenant_41cd677709e6_attr": "41cd677709e6",
    "_fromType": "DeviceProxyOut",
    "_toType": "SoftwareProxyIn"
  },
  {
    "_key": "41cd677709e6_hasSoftware68",
    "_from": "DeviceProxyOut/41cd677709e6_device11",
    "_to": "SoftwareProxyIn/41cd677709e6_software26",
    "created": 1757903278.625193,
    "expired": 9223372036854775807,
    "tenant_41cd677709e6_attr": "41cd677709e6",
    "_fromType": "DeviceProxyOut",
    "_toType": "SoftwareProxyIn"
  },
  {
    "_key": "41cd677709e6_hasSoftware69",
    "_from": "DeviceProxyOut/41cd677709e6_device30",
    "_to": "SoftwareProxyIn/41cd677709e6_software7",
    "created": 1757903278.625213,
    "expired": 9223372036854775807,
    "tenant_41cd677709e6_attr": "41cd677709e6",
    "_fromType": "DeviceProxyOut",
    "_toType": "SoftwareProxyIn"
  },
  {
    "_key": "41cd677709e6_hasSoftware70",
    "_from": "DeviceProxyOut/41cd677709e6_device37",
    "_to": "SoftwareProxyIn/41cd677709e6_software21",
    "created": 1757903278.625234,
    "expired": 9223372036854775807,
    "tenant_41cd677709e6_attr": "41cd677709e6",
    "_fromType": "DeviceProxyOut",
    "_toType": "SoftwareProxyIn"
  },
  {
    "_key": "41cd677709e6_hasSoftware71",
    "_from": "DeviceProxyOut/41cd677709e6_device9",
    "_to": "SoftwareProxyIn/41cd677709e6_software46",
    "created": 1757903278.625255,
    "expired": 9223372036854775807,
    "tenant_41cd677709e6_attr": "41cd677709e6",
    "_fromType": "DeviceProxyOut",
    "_toType": "SoftwareProxyIn"
  },
  {
    "_key": "41cd677709e6_hasSoftware72",
    "_from": "DeviceProxyOut/41cd677709e6_device9",
    "_to": "SoftwareProxyIn/41cd677709e6_software54",
    "created": 1757903278.625276,
    "expired": 9223372036854775807,
    "tenant_41cd677709e6_attr": "41cd677709e6",
    "_fromType": "DeviceProxyOut",
    "_toType": "SoftwareProxyIn"
  },
  {
    "_key": "41cd677709e6_hasSoftware73",
    "_from": "DeviceProxyOut/41cd677709e6_device37",
    "_to": "SoftwareProxyIn/41cd677709e6_software1",
    "created": 1757903278.625298,
    "expired": 9223372036854775807,
    "tenant_41cd677709e6_attr": "41cd677709e6",
    "_fromType": "DeviceProxyOut",
    "_toType": "SoftwareProxyIn"
  },
  {
    "_key": "41cd677709e6_hasSoftware74",
    "_from": "DeviceProxyOut/41cd677709e6_device2",
    "_to": "SoftwareProxyIn/41cd677709e6_software7",
    "created": 1757903278.62532,
    "expired": 9223372036854775807,
    "tenant_41cd677709e6_attr": "41cd677709e6",
    "_fromType": "DeviceProxyOut",
    "_toType": "SoftwareProxyIn"
  },
  {
    "_key": "41cd677709e6_hasSoftware75",
    "_from": "DeviceProxyOut/41cd677709e6_device33",
    "_to": "SoftwareProxyIn/41cd677709e6_software15",
    "created": 1757903278.625342,
    "expired": 9223372036854775807,
    "tenant_41cd677709e6_attr": "41cd677709e6",
    "_fromType": "DeviceProxyOut",
    "_toType": "SoftwareProxyIn"
  },
  {
    "_key": "41cd677709e6_hasSoftware76",
    "_from": "DeviceProxyOut/41cd677709e6_device19",
    "_to": "SoftwareProxyIn/41cd677709e6_software36",
    "created": 1757903278.625364,
    "expired": 9223372036854775807,
    "tenant_41cd677709e6_attr": "41cd677709e6",
    "_fromType": "DeviceProxyOut",
    "_toType": "SoftwareProxyIn"
  },
  {
    "_key": "41cd677709e6_hasSoftware77",
    "_from": "DeviceProxyOut/41cd677709e6_device28",
    "_to": "SoftwareProxyIn/41cd677709e6_software46",
    "created": 1757903278.625387,
    "expired": 9223372036854775807,
    "tenant_41cd677709e6_attr": "41cd677709e6",
    "_fromType": "DeviceProxyOut",
    "_toType": "SoftwareProxyIn"
  },
  {
    "_key": "41cd677709e6_hasSoftware78",
    "_from": "DeviceProxyOut/41cd677709e6_device15",
    "_to": "SoftwareProxyIn/41cd677709e6_software12",
    "created": 1757903278.625412,
    "expired": 9223372036854775807,
    "tenant_41cd677709e6_attr": "41cd677709e6",
    "_fromType": "DeviceProxyOut",
    "_toType": "SoftwareProxyIn"
  },
  {
    "_key": "41cd677709e6_hasSoftware79",
    "_from": "DeviceProxyOut/41cd677709e6_device4",
    "_to": "SoftwareProxyIn/41cd677709e6_software55",
    "created": 1757903278.625437,
    "expired": 9223372036854775807,
    "tenant_41cd677709e6_attr": "41cd677709e6",
    "_fromType": "DeviceProxyOut",
    "_toType": "SoftwareProxyIn"
  },
  {
    "_key": "41cd677709e6_hasSoftware80",
    "_from": "DeviceProxyOut/41cd677709e6_device5",
    "_to": "SoftwareProxyIn/41cd677709e6_software56",
    "created": 1757903278.625462,
    "expired": 9223372036854775807,
    "tenant_41cd677709e6_attr": "41cd677709e6",
    "_fromType": "DeviceProxyOut",
    "_toType": "SoftwareProxyIn"
  }
]